pipeline_sdk_test49/__init__.py
pipeline_sdk_test49/auth_service.py
pipeline_sdk_test49/inference_pipeline.py
pipeline_sdk_test49/model_inference_dsl_component.py
pipeline_sdk_test49/model_train_dsl_component.py
pipeline_sdk_test49/model_validate_dsl_component.py
pipeline_sdk_test49/pipeline_util.py
pipeline_sdk_test49/run_inference_pipeline.py
pipeline_sdk_test49/run_training_pipeline.py
pipeline_sdk_test49/run_validate_pipeline.py
pipeline_sdk_test49/train_pipeline.py
pipeline_sdk_test49/validate_pipeline.py
pipeline_sdk_test49-1.0.0.dist-info/METADATA
pipeline_sdk_test49-1.0.0.dist-info/WHEEL
pipeline_sdk_test49-1.0.0.dist-info/top_level.txt
pipeline_sdk_test49-1.0.0.dist-info/RECORD
